Workbook

Sheet RESUMEN ANUAL
A1: RESUMEN FINANCIERO ANUAL 2026 | G1: GANANCIAS POR SOCIO
A3: MES | B3: TOTAL INGRESO | C3: TOTAL SALIDA | D3: TOTAL NETO | E3: MARGEN NETO | G3: MES | H3: ANGEL | I3: RONAL | J3: NORIS
A4: Enero | B4: ='Enero CTV'!B2 -> 31124 | C4: ='Enero CTV'!B3 -> 15493.8 | D4: ='Enero CTV'!B4 -> 15630.2 | E4: =IFERROR(D4/B4,0) -> 0.50219124 | G4: Enero | H4: =$D4/3 -> 5210.0667 | I4: =$D4/3 -> 5210.0667 | J4: =$D4/3 -> 5210.0667
A5: Febrero | B5: ='Febrero CTV'!B2 -> 25583.5 | C5: ='Febrero CTV'!B3 -> 13926.5 | D5: ='Febrero CTV'!B4 -> 11657 | E5: =IFERROR(D5/B5,0) -> 0.45564524 | G5: Febrero | H5: =$D5/3 -> 3885.6667 | I5: =$D5/3 -> 3885.6667 | J5: =$D5/3 -> 3885.6667
A6: Marzo | B6: ='Marzo CTV'!B2 -> 31855.5 | C6: ='Marzo CTV'!B3 -> 16432.8 | D6: ='Marzo CTV'!B4 -> 15422.7 | E6: =IFERROR(D6/B6,0) -> 0.48414559 | G6: Marzo | H6: =$D6/3 -> 5140.9 | I6: =$D6/3 -> 5140.9 | J6: =$D6/3 -> 5140.9
A7: Abril | B7: ='Abril CTV'!B2 -> 26317.5 | C7: ='Abril CTV'!B3 -> 15095.6 | D7: ='Abril CTV'!B4 -> 11221.9 | E7: =IFERROR(D7/B7,0) -> 0.42640448 | G7: Abril | H7: =$D7/3 -> 3740.6333 | I7: =$D7/3 -> 3740.6333 | J7: =$D7/3 -> 3740.6333
A8: Mayo | B8: ='Mayo CTV'!B2 -> 34861 | C8: ='Mayo CTV'!B3 -> 12959.4 | D8: ='Mayo CTV'!B4 -> 21901.6 | E8: =IFERROR(D8/B8,0) -> 0.62825507 | G8: Mayo | H8: =$D8/3 -> 7300.5333 | I8: =$D8/3 -> 7300.5333 | J8: =$D8/3 -> 7300.5333
A9: Junio | B9: ='Junio CTV'!B2 -> 22873 | C9: ='Junio CTV'!B3 -> 13869.84 | D9: ='Junio CTV'!B4 -> 9003.16 | E9: =IFERROR(D9/B9,0) -> 0.39361518 | G9: Junio | H9: =$D9/3 -> 3001.0533 | I9: =$D9/3 -> 3001.0533 | J9: =$D9/3 -> 3001.0533
A10: Julio | B10: ='Julio CTV'!B2 -> 0 | C10: ='Julio CTV'!B3 -> 0 | D10: ='Julio CTV'!B4 -> 0 | E10: =IFERROR(D10/B10,0) -> 0 | G10: Julio | H10: =$D10/3 -> 0 | I10: =$D10/3 -> 0 | J10: =$D10/3 -> 0
A11: Agosto | B11: ='Agosto CTV'!B2 -> 0 | C11: ='Agosto CTV'!B3 -> 0 | D11: ='Agosto CTV'!B4 -> 0 | E11: =IFERROR(D11/B11,0) -> 0 | G11: Agosto | H11: =$D11/3 -> 0 | I11: =$D11/3 -> 0 | J11: =$D11/3 -> 0
A12: Septiembre | B12: ='Septiembre CTV'!B2 -> 0 | C12: ='Septiembre CTV'!B3 -> 0 | D12: ='Septiembre CTV'!B4 -> 0 | E12: =IFERROR(D12/B12,0) -> 0 | G12: Septiembre | H12: =$D12/3 -> 0 | I12: =$D12/3 -> 0 | J12: =$D12/3 -> 0
A13: Octubre | B13: ='Octubre CTV'!B2 -> 0 | C13: ='Octubre CTV'!B3 -> 0 | D13: ='Octubre CTV'!B4 -> 0 | E13: =IFERROR(D13/B13,0) -> 0 | G13: Octubre | H13: =$D13/3 -> 0 | I13: =$D13/3 -> 0 | J13: =$D13/3 -> 0
A14: Noviembre | B14: ='Noviembre CTV'!B2 -> 0 | C14: ='Noviembre CTV'!B3 -> 0 | D14: ='Noviembre CTV'!B4 -> 0 | E14: =IFERROR(D14/B14,0) -> 0 | G14: Noviembre | H14: =$D14/3 -> 0 | I14: =$D14/3 -> 0 | J14: =$D14/3 -> 0
A15: Diciembre | B15: ='Diciembre CTV'!B2 -> 0 | C15: ='Diciembre CTV'!B3 -> 0 | D15: ='Diciembre CTV'!B4 -> 0 | E15: =IFERROR(D15/B15,0) -> 0 | G15: Diciembre | H15: =$D15/3 -> 0 | I15: =$D15/3 -> 0 | J15: =$D15/3 -> 0
A16: TOTAL ANUAL | B16: =SUM(B4:B15) -> 172614.5 | C16: =SUM(C4:C15) -> 87777.94 | D16: =SUM(D4:D15) -> 84836.56 | E16: =IFERROR(D16/B16,0) -> 0.49147992 | G16: TOTAL ANUAL | H16: =SUM(H4:H15) -> 28278.853 | I16: =SUM(I4:I15) -> 28278.853 | J16: =SUM(J4:J15) -> 28278.853
A55: MES | B55: TOTAL INGRESO | C55: TOTAL SALIDA | D55: TOTAL NETO
A56: Enero | B56: =IF(B4=0,NA(),B4) -> 31124 | C56: =IF(C4=0,NA(),C4) -> 15493.8 | D56: =IFERROR(B56-C56,"") -> 15630.2
A57: Febrero | B57: =IF(B5=0,NA(),B5) -> 25583.5 | C57: =IF(C5=0,NA(),C5) -> 13926.5 | D57: =IFERROR(B57-C57,"") -> 11657
A58: Marzo | B58: =IF(B6=0,NA(),B6) -> 31855.5 | C58: =IF(C6=0,NA(),C6) -> 16432.8 | D58: =IFERROR(B58-C58,"") -> 15422.7
A59: Abril | B59: =IF(B7=0,NA(),B7) -> 26317.5 | C59: =IF(C7=0,NA(),C7) -> 15095.6 | D59: =IFERROR(B59-C59,"") -> 11221.9
A60: Mayo | B60: =IF(B8=0,NA(),B8) -> 34861 | C60: =IF(C8=0,NA(),C8) -> 12959.4 | D60: =IFERROR(B60-C60,"") -> 21901.6
A61: Junio | B61: =IF(B9=0,NA(),B9) -> 22873 | C61: =IF(C9=0,NA(),C9) -> 13869.84 | D61: =IFERROR(B61-C61,"") -> 9003.16
A62: Julio | B62: =IF(B10=0,NA(),B10) -> #N/A | C62: =IF(C10=0,NA(),C10) -> #N/A | D62: =IFERROR(B62-C62,"")
A63: Agosto | B63: =IF(B11=0,NA(),B11) -> #N/A | C63: =IF(C11=0,NA(),C11) -> #N/A | D63: =IFERROR(B63-C63,"")
A64: Septiembre | B64: =IF(B12=0,NA(),B12) -> #N/A | C64: =IF(C12=0,NA(),C12) -> #N/A | D64: =IFERROR(B64-C64,"")
A65: Octubre | B65: =IF(B13=0,NA(),B13) -> #N/A | C65: =IF(C13=0,NA(),C13) -> #N/A | D65: =IFERROR(B65-C65,"")
A66: Noviembre | B66: =IF(B14=0,NA(),B14) -> #N/A | C66: =IF(C14=0,NA(),C14) -> #N/A | D66: =IFERROR(B66-C66,"")
A67: Diciembre | B67: =IF(B15=0,NA(),B15) -> #N/A | C67: =IF(C15=0,NA(),C15) -> #N/A | D67: =IFERROR(B67-C67,"")
A68: TOTAL ANUAL | B68: =SUM(B56:B67) -> #N/A | C68: =SUM(C56:C67) -> #N/A | D68: =SUM(D56:D67) -> 84836.56

Sheet Enero CTV
A1: 46023
A2: TOTAL INGRESO | B2: =D6+'Enero Internet'!D2+'Enero Vta Mat'!B2 -> 31124
A3: TOTAL SALIDA | B3: ='Enero Pagos'!B2+'Enero Gastos'!B2+'Enero Compra Mat'!C2 -> 15493.8
A4: TOTAL NETO | B4: =B2-B3 -> 15630.2
A6: INGRESO DETALLADO CTV - ENERO 2026 | D6: =SUM(D9:D108) -> 11617
A8: CLIENTES | B8: MONTO PAGO | C8: DETALLE PAGO | D8: SUB TOTAL
A9: 2 | B9: 250 | D9: =IF(A9="","",A9*B9) -> 500
A10: 26 | B10: 50 | D10: =IF(A10="","",A10*B10) -> 1300
A11: 34 | B11: 100 | D11: =IF(A11="","",A11*B11) -> 3400
A12: 7 | B12: 120 | D12: =IF(A12="","",A12*B12) -> 840
A13: 8 | B13: 150 | D13: =IF(A13="","",A13*B13) -> 1200
A14: 8 | B14: 200 | D14: =IF(A14="","",A14*B14) -> 1600
A15: 1 | B15: 225 | D15: =IF(A15="","",A15*B15) -> 225
A16: 1 | B16: 70 | D16: =IF(A16="","",A16*B16) -> 70
A17: 1 | B17: 252 | D17: =IF(A17="","",A17*B17) -> 252
A18: 1 | B18: 32 | D18: =IF(A18="","",A18*B18) -> 32
A19: 1 | B19: 80 | D19: =IF(A19="","",A19*B19) -> 80
A20: 1 | B20: 40 | D20: =IF(A20="","",A20*B20) -> 40
... A29: 1 | B29: 75 | D29: =IF(A29="","",A29*B29) -> 75
D30: =IF(A30="","",A30*B30)
D31: =IF(A31="","",A31*B31)
D32: =IF(A32="","",A32*B32)
D33: =IF(A33="","",A33*B33)
D34: =IF(A34="","",A34*B34)
D35: =IF(A35="","",A35*B35)
D36: =IF(A36="","",A36*B36)
D37: =IF(A37="","",A37*B37)
D38: =IF(A38="","",A38*B38)
D39: =IF(A39="","",A39*B39)
D40: =IF(A40="","",A40*B40)
D41: =IF(A41="","",A41*B41)
... D108: =IF(A108="","",A108*B108)

Sheet Enero Internet
A1: INGRESO DETALLADO INTERNET - ENERO 2026
A2: TOTAL | D2: =SUM(D5:D104) -> 18865
A4: CLIENTES | B4: MONTO PAGO | C4: DETALLE PAGO | D4: SUB TOTAL
A5: 7 | B5: 110 | D5: =IF(A5="","",A5*B5) -> 770
A6: 42 | B6: 120 | D6: =IF(A6="","",A6*B6) -> 5040
A7: 4 | B7: 380 | D7: =IF(A7="","",A7*B7) -> 1520
A8: 14 | B8: 240 | D8: =IF(A8="","",A8*B8) -> 3360
A9: 5 | B9: 360 | D9: =IF(A9="","",A9*B9) -> 1800
A10: 2 | B10: 50 | D10: =IF(A10="","",A10*B10) -> 100
A11: 3 | B11: 220 | D11: =IF(A11="","",A11*B11) -> 660
A12: 1 | B12: 350 | D12: =IF(A12="","",A12*B12) -> 350
A13: 1 | B13: 320 | D13: =IF(A13="","",A13*B13) -> 320
A14: 1 | B14: 170 | D14: =IF(A14="","",A14*B14) -> 170
A15: 1 | B15: 205 | D15: =IF(A15="","",A15*B15) -> 205
A16: 1 | B16: 1050 | D16: =IF(A16="","",A16*B16) -> 1050
... A27: 1 | B27: 160 | D27: =IF(A27="","",A27*B27) -> 160
D28: =IF(A28="","",A28*B28)
D29: =IF(A29="","",A29*B29)
D30: =IF(A30="","",A30*B30)
D31: =IF(A31="","",A31*B31)
D32: =IF(A32="","",A32*B32)
D33: =IF(A33="","",A33*B33)
D34: =IF(A34="","",A34*B34)
D35: =IF(A35="","",A35*B35)
D36: =IF(A36="","",A36*B36)
D37: =IF(A37="","",A37*B37)
D38: =IF(A38="","",A38*B38)
D39: =IF(A39="","",A39*B39)
... D104: =IF(A104="","",A104*B104)

Sheet Enero Vta Mat
A1: VENTA DE MATERIALES - ENERO 2026
A2: TOTAL | B2: =SUM(B5:B54) -> 642
A4: CONCEPTO | B4: MONTO
A5: 15 mts cable coaxial mas 2 conectores | B5: 42.5
A6: reuter 02 cada uno a 190 | B6: 380
A7: 20 mts cable coaxial | B7: 50
A8: 01 sintonizador | B8: 90
A9: 20 mts cable de red mas 2 conectores RJ 45 | B9: 55
A10: 01 control | B10: 24.5

Sheet Enero Pagos
A1: PAGOS DE: ALQUILERES, ENERGÍA, IPTv, RENTAS Y OTROS - ENERO 2026
A2: TOTAL | B2: =SUM(B5:B54) -> 14765.3
A4: CONCEPTO | B4: MONTO
A5: PAGO ALQUILER OFICINA | B5: 400
A6: PAGO ALQUILER CABECERA | B6: 800
A7: PAGO ENERGÍA OFICINA | B7: 29
A8: PAGO ENERGÍA CABECERA | B8: 618.8
A9: PAGO 02 LÍNEAS CLARO CELULAR | B9: 31
A10: PAGO ALQUILER POSTES ELECTRO P. | B10: 100
A11: PAGO RENTA, PRONATEL Y CONTADORA | B11: 150.7
A12: PAGO TÉCNICO | B12: 1800
A13: PAGO SECRETARIA | B13: 1200
A14: PAGO A. RESPONSABLE | B14: 800
A15: PAGO INTERNET CLARO | B15: 6195
A16: PAGO IPTU LIGA 1 Y CARLOS | B16: 2640.8

Sheet Enero Gastos
A1: GASTOS OLLACHEA, COMISIONES Y OTROS - ENERO 2026
A2: TOTAL | B2: =SUM(B5:B54) -> 528.5
A4: CONCEPTO | B4: MONTO
A5: compra de pila | B5: 8
A6: un cuaderno | B6: 2.5
A7: lapizeros | B7: 5
A8: posit notas | B8: 2.5
A9: cloro y poet | B9: 6.5
A10: mica e impresión | B10: 6
A11: cinta e impresión mas 1 mica | B11: 4.5
A12: detergente mas cloro | B12: 3.5
A13: poet cabezera | B13: 5
A14: bruno | B14: 45
A15: protector de pantalla para celular | B15: 10
A16: traslado de personal a ollachea combustible | B16: 60
... A29: pasaje a juliaca pago de electro | B29: 20

Sheet Enero Compra Mat
A1: COMPRA DE MATERIALES - ENERO 2026
A2: TOTAL | C2: =SUM(C5:C54) -> 200
A4: CONCEPTO | B4: CANTIDAD | C4: MONTO
A5: cable coaxial | C5: 200

Sheet Febrero CTV
A1: 46054
A2: TOTAL INGRESO | B2: =D6+'Febrero Internet'!D2+'Febrero Vta Mat'!B2 -> 25583.5
A3: TOTAL SALIDA | B3: ='Febrero Pagos'!B2+'Febrero Gastos'!B2+'Febrero Compra Mat'!C2 -> 13926.5
A4: TOTAL NETO | B4: =B2-B3 -> 11657
A6: INGRESO DETALLADO C TV - FEBRERO 2026 | D6: =SUM(D9:D108) -> 8831
A8: CLIENTES | B8: MONTO PAGO | C8: DETALLE PAGO | D8: SUB TOTAL
A9: 38 | B9: 50 | D9: =IF(A9="","",A9*B9) -> 1900
A10: 8 | B10: 150 | D10: =IF(A10="","",A10*B10) -> 1200
A11: 4 | B11: 120 | D11: =IF(A11="","",A11*B11) -> 480
A12: 33 | B12: 100 | D12: =IF(A12="","",A12*B12) -> 3300
A13: 5 | B13: 200 | D13: =IF(A13="","",A13*B13) -> 1000
A14: 1 | B14: 167 | D14: =IF(A14="","",A14*B14) -> 167
A15: 1 | B15: 39 | D15: =IF(A15="","",A15*B15) -> 39
A16: 1 | B16: 155 | D16: =IF(A16="","",A16*B16) -> 155
A17: 1 | B17: 35 | D17: =IF(A17="","",A17*B17) -> 35
A18: 1 | B18: 305 | D18: =IF(A18="","",A18*B18) -> 305
A19: 1 | B19: 250 | D19: =IF(A19="","",A19*B19) -> 250
D20: =IF(A20="","",A20*B20)
D21: =IF(A21="","",A21*B21)
D22: =IF(A22="","",A22*B22)
D23: =IF(A23="","",A23*B23)
D24: =IF(A24="","",A24*B24)
D25: =IF(A25="","",A25*B25)
D26: =IF(A26="","",A26*B26)
D27: =IF(A27="","",A27*B27)
D28: =IF(A28="","",A28*B28)
D29: =IF(A29="","",A29*B29)
D30: =IF(A30="","",A30*B30)
D31: =IF(A31="","",A31*B31)
... D108: =IF(A108="","",A108*B108)

Sheet Febrero Internet
A1: INGRESO DETALLADO INTERNET - FEBRERO 2026
A2: TOTAL | D2: =SUM(D5:D104) -> 16425
A4: CLIENTES | B4: MONTO PAGO | C4: DETALLE PAGO | D4: SUB TOTAL
A5: 20 | B5: 240 | D5: =IF(A5="","",A5*B5) -> 4800
A6: 46 | B6: 120 | D6: =IF(A6="","",A6*B6) -> 5520
A7: 2 | B7: 135 | D7: =IF(A7="","",A7*B7) -> 270
A8: 8 | B8: 110 | D8: =IF(A8="","",A8*B8) -> 880
A9: 4 | B9: 220 | D9: =IF(A9="","",A9*B9) -> 880
A10: 2 | B10: 150 | D10: =IF(A10="","",A10*B10) -> 300
A11: 1 | B11: 1000 | D11: =IF(A11="","",A11*B11) -> 1000
A12: 1 | B12: 380 | D12: =IF(A12="","",A12*B12) -> 380
A13: 1 | B13: 360 | D13: =IF(A13="","",A13*B13) -> 360
A14: 1 | B14: 440 | D14: =IF(A14="","",A14*B14) -> 440
A15: 1 | B15: 700 | D15: =IF(A15="","",A15*B15) -> 700
A16: 1 | B16: 115 | D16: =IF(A16="","",A16*B16) -> 115
... A19: 1 | B19: 170 | D19: =IF(A19="","",A19*B19) -> 170
D20: =IF(A20="","",A20*B20)
D21: =IF(A21="","",A21*B21)
D22: =IF(A22="","",A22*B22)
D23: =IF(A23="","",A23*B23)
D24: =IF(A24="","",A24*B24)
D25: =IF(A25="","",A25*B25)
D26: =IF(A26="","",A26*B26)
D27: =IF(A27="","",A27*B27)
D28: =IF(A28="","",A28*B28)
D29: =IF(A29="","",A29*B29)
D30: =IF(A30="","",A30*B30)
D31: =IF(A31="","",A31*B31)
... D104: =IF(A104="","",A104*B104)

Sheet Febrero Vta Mat
A1: VENTA DE MATERIALES - FEBRERO 2026
A2: TOTAL | B2: =SUM(B5:B54) -> 327.5
A4: CONCEPTO | B4: MONTO
A5: 3 metros cable blanco / 2 conectores metalicos | B5: 12.5
A6: 4 conectores | B6: 10
A7: sintonizador | B7: 90
A8: reuter | B8: 190
A9: 6 metros cable | B9: 15
A10: cable red | B10: 10

Sheet Febrero Pagos
A1: PAGOS DE: ALQUILERES, ENERGÍA, IPTV, RENTAS Y OTROS - FEBRERO 2026
A2: TOTAL | B2: =SUM(B5:B54) -> 13400.5
A4: CONCEPTO | B4: MONTO
A5: PAGO ALQUILER OFICINA | B5: 400
A6: PAGO ALQUILER CABECERA | B6: 800
A7: PAGO ENERGÍA OFICINA | B7: 35.4
A8: PAGO ENERGÍA CABECERA | B8: 558.4
A9: PAGO 02 LÍNEAS CLARO CELULAR | B9: 29.9
A10: PAGO ALQUILER POSTES ELECTRO P. | B10: 105
A11: PAGO RENTA, PRONATEL Y CONTADORA | B11: 158
A12: PAGO TÉCNICO | B12: 1800
A13: PAGO SECRETARIA | B13: 1200
A14: PAGO A. RESPONSABLE | B14: 800
A15: PAGO INTERNET CLARO | B15: 6205
A16: PAGO IPTV LIGA F Y CARLOS | B16: 1308.8

Sheet Febrero Gastos
A1: GASTOS OLLACHEA, COMISIONES Y OTROS - FEBRERO 2026
A2: TOTAL | B2: =SUM(B5:B54) -> 322
A4: CONCEPTO | B4: MONTO
A5: GAS PARA LA SECRETARIA | B5: 57
A6: GUANTES NARANJA | B6: 5
A7: AMBIENTADOR | B7: 15
A8: POETH | B8: 5
A9: LAPICERO NEGRO | B9: 1.5
A10: BOLETA | B10: 5.5
A11: POR RECOJO DE DINERO QUINCENAL | B11: 70
A12: POR RECOJO DE DINERO QUINCENAL 3 ALMUERZOS | B12: 24
A13: ADORNO ALA OFICINA POR CARNAVAL | B13: 5
A14: POR RECOJO DE DINERO FIN DE MES | B14: 70
A15: POR RECOJO DE DINERO 3 ALMUERZOS | B15: 24
A16: PASAJE A JULIACA PAGOS DE INTERNET Y ELECTRO | B16: 40

Sheet Febrero Compra Mat
A1: COMPRA DE MATERIALES - FEBRERO 2026
A2: TOTAL | C2: =SUM(C5:C54) -> 204
A4: CONCEPTO | B4: CANTIDAD | C4: MONTO
A5: presinto para bruno | C5: 4
A6: recibo de 2 millares con logo de la empresa | C6: 200

Sheet Marzo CTV
A1: MARZO 2025
A2: TOTAL INGRESO | B2: =D6+'Marzo Internet'!D2+'Marzo Vta Mat'!B2 -> 31855.5
A3: TOTAL SALIDA | B3: ='Marzo Pagos'!B2+'Marzo Gastos'!B2+'Marzo Compra Mat'!C2 -> 16432.8
A4: TOTAL NETO | B4: =B2-B3 -> 15422.7
A6: INGRESO DETALLADO CTV - MARZO 2025 | D6: =SUM(D9:D108) -> 10222
A8: CLIENTES | B8: MONTO PAGO | C8: DETALLE PAGO | D8: SUB TOTAL
A9: 38 | B9: 100 | D9: =IF(A9="","",A9*B9) -> 3800
A10: 40 | B10: 50 | D10: =IF(A10="","",A10*B10) -> 2000
A11: 5 | B11: 200 | D11: =IF(A11="","",A11*B11) -> 1000
A12: 3 | B12: 150 | D12: =IF(A12="","",A12*B12) -> 450
A13: 2 | B13: 75 | D13: =IF(A13="","",A13*B13) -> 150
A14: 2 | B14: 250 | D14: =IF(A14="","",A14*B14) -> 500
A15: 1 | B15: 230 | D15: =IF(A15="","",A15*B15) -> 230
A16: 1 | B16: 380 | D16: =IF(A16="","",A16*B16) -> 380
A17: 1 | B17: 340 | D17: =IF(A17="","",A17*B17) -> 340
A18: 1 | B18: 305 | D18: =IF(A18="","",A18*B18) -> 305
A19: 1 | B19: 338 | D19: =IF(A19="","",A19*B19) -> 338
A20: 1 | B20: 140 | D20: =IF(A20="","",A20*B20) -> 140
... A26: 1 | B26: 157 | D26: =IF(A26="","",A26*B26) -> 157
D27: =IF(A27="","",A27*B27)
D28: =IF(A28="","",A28*B28)
D29: =IF(A29="","",A29*B29)
D30: =IF(A30="","",A30*B30)
D31: =IF(A31="","",A31*B31)
D32: =IF(A32="","",A32*B32)
D33: =IF(A33="","",A33*B33)
D34: =IF(A34="","",A34*B34)
D35: =IF(A35="","",A35*B35)
D36: =IF(A36="","",A36*B36)
D37: =IF(A37="","",A37*B37)
D38: =IF(A38="","",A38*B38)
... D108: =IF(A108="","",A108*B108)

Sheet Marzo Internet
A1: INGRESO DETALLADO INTERNET - MARZO 2025
A2: TOTAL | D2: =SUM(D5:D104) -> 20940
A4: CLIENTES | B4: MONTO PAGO | C4: DETALLE PAGO | D4: SUB TOTAL
A5: 24 | B5: 240 | D5: =IF(A5="","",A5*B5) -> 5760
A6: 50 | B6: 120 | D6: =IF(A6="","",A6*B6) -> 6000
A7: 10 | B7: 110 | D7: =IF(A7="","",A7*B7) -> 1100
A8: 4 | B8: 360 | D8: =IF(A8="","",A8*B8) -> 1440
A9: 3 | B9: 220 | D9: =IF(A9="","",A9*B9) -> 660
A10: 3 | B10: 135 | D10: =IF(A10="","",A10*B10) -> 405
A11: 2 | B11: 1050 | D11: =IF(A11="","",A11*B11) -> 2100
A12: 1 | B12: 150 | D12: =IF(A12="","",A12*B12) -> 150
A13: 1 | B13: 115 | D13: =IF(A13="","",A13*B13) -> 115
A14: 1 | B14: 270 | D14: =IF(A14="","",A14*B14) -> 270
A15: 1 | B15: 350 | D15: =IF(A15="","",A15*B15) -> 350
A16: 1 | B16: 330 | D16: =IF(A16="","",A16*B16) -> 330
... A21: 1 | B21: 170 | D21: =IF(A21="","",A21*B21) -> 170
D22: =IF(A22="","",A22*B22)
D23: =IF(A23="","",A23*B23)
D24: =IF(A24="","",A24*B24)
D25: =IF(A25="","",A25*B25)
D26: =IF(A26="","",A26*B26)
D27: =IF(A27="","",A27*B27)
D28: =IF(A28="","",A28*B28)
D29: =IF(A29="","",A29*B29)
D30: =IF(A30="","",A30*B30)
D31: =IF(A31="","",A31*B31)
D32: =IF(A32="","",A32*B32)
D33: =IF(A33="","",A33*B33)
... D104: =IF(A104="","",A104*B104)

Sheet Marzo Vta Mat
A1: VENTA DE MATERIALES - MARZO 2025
A2: TOTAL | B2: =SUM(B5:B54) -> 693.5
A4: CONCEPTO | B4: MONTO
A5: reuter 170 mas fibra 36 | B5: 206
A6: cable 2 mt y 3 conectores metalicos | B6: 12.5
A7: 1 ONU mas sintonizador digital | B7: 250
A8: LTB mas ONU (Pagara en 3 partes) | B8: 65
A9: reuter | B9: 160

Sheet Marzo Pagos
A1: PAGOS DE: ALQUILERES, ENERGÍA, IPTU, RENTAS Y OTROS - MARZO 2025
A2: TOTAL | B2: =SUM(B5:B54) -> 13167.8
A4: CONCEPTO | B4: MONTO
A5: PAGO ALQUILER OFICINA | B5: 400
A6: PAGO ALQUILER CABECERA | B6: 800
A7: PAGO ENERGÍA OFICINA | B7: 21
A8: PAGO ENERGÍA CABECERA | B8: 460
A9: PAGO 02 LÍNEAS CLARO CELULAR | B9: 30
A10: PAGO ALQUILER POSTES ELECTRO P. | B10: 105
A11: PAGO RENTA, PRONATEL Y CONTADORA | B11: 155
A12: PAGO TÉCNICO | B12: 1800
A13: PAGO SECRETARIA | B13: 1200
A14: PAGO A. RESPONSABLE | B14: 800
A15: PAGO INTERNET CLARO | B15: 6088
A16: PAGO CARLOS IPTV LIGA UNO AI | B16: 1308.8

Sheet Marzo Gastos
A1: GASTOS OLLACHEA, COMISIONES Y OTROS - MARZO 2025
A2: TOTAL | B2: =SUM(B5:B54) -> 360
A4: CONCEPTO | B4: MONTO
A5: POETT CABECERA | B5: 8
A6: CLOROX | B6: 5
A7: GAS- PARA SECRETARIA OLLACHEA | B7: 90
A8: ENVIO DE ONUS DE AREQUIPA - JULIACA - CARLOS | B8: 20
A9: RECOJO DE ENCOMIENDA ONUS | B9: 30
A10: ENVIO DE ONUS JULIACA - OLLACHEA | B10: 15
A11: RECOJO DE DINERO FIN DE MES | B11: 70
A12: TRASLADO DE PERSONAL A OLLACHE | B12: 50
A13: CENA DE RECOJO DE DINERO FIN DE MES | B13: 32
A14: VIGENCIA DE PODER | B14: 40

Sheet Marzo Compra Mat
A1: COMPRA DE MATERIALES - MARZO 2025
A2: TOTAL | C2: =SUM(C5:C54) -> 2905
A4: CONCEPTO | B4: CANTIDAD | C4: MONTO
A5: CINTA NEGRA 3M | B5: 1 | C5: 5
A6: ONUS CADA UNO A 130 | B6: 20 | C6: 2600
A7: SINTONIZADOR DIGITAL | B7: 6 | C7: 300

Sheet Abril CTV
A1: 46113
A2: TOTAL INGRESO | B2: =D6+'Abril Internet'!D2+'Abril Vta Mat'!B2 -> 26317.5
A3: TOTAL SALIDA | B3: ='Abril Pagos'!B2+'Abril gastos'!B2+'Abril Compra Mat'!C2 -> 15095.6
A4: TOTAL NETO | B4: =B2-B3 -> 11221.9
A6: INGRESO DETALLADO CTV - ABRIL 2025 | D6: =SUM(D9:D108) -> 11030
A8: CLIENTES | B8: MONTO PAGO | C8: DETALLE PAGO | D8: SUB TOTAL
A9: 31 | B9: 100 | D9: =IF(A9="","",A9*B9) -> 3100
A10: 37 | B10: 50 | D10: =IF(A10="","",A10*B10) -> 1850
A11: 16 | B11: 150 | D11: =IF(A11="","",A11*B11) -> 2400
A12: 5 | B12: 200 | D12: =IF(A12="","",A12*B12) -> 1000
A13: 7 | B13: 120 | D13: =IF(A13="","",A13*B13) -> 840
A14: 3 | B14: 250 | D14: =IF(A14="","",A14*B14) -> 750
A15: 1 | B15: 70 | D15: =IF(A15="","",A15*B15) -> 70
A16: 1 | B16: 305 | D16: =IF(A16="","",A16*B16) -> 305
A17: 1 | B17: 310 | D17: =IF(A17="","",A17*B17) -> 310
A18: 1 | B18: 300 | D18: =IF(A18="","",A18*B18) -> 300
A19: 1 | B19: 105 | D19: =IF(A19="","",A19*B19) -> 105
D20: =IF(A20="","",A20*B20)
D21: =IF(A21="","",A21*B21)
D22: =IF(A22="","",A22*B22)
D23: =IF(A23="","",A23*B23)
D24: =IF(A24="","",A24*B24)
D25: =IF(A25="","",A25*B25)
D26: =IF(A26="","",A26*B26)
D27: =IF(A27="","",A27*B27)
D28: =IF(A28="","",A28*B28)
D29: =IF(A29="","",A29*B29)
D30: =IF(A30="","",A30*B30)
D31: =IF(A31="","",A31*B31)
... D108: =IF(A108="","",A108*B108)

Sheet Abril Internet
A1: INGRESO DETALLADO INTERNET - ABRIL 2026
A2: TOTAL | D2: =SUM(D5:D104) -> 14575
A4: CLIENTES | B4: MONTO PAGO | C4: DETALLE PAGO | D4: SUB TOTAL
A5: 8 | B5: 240 | D5: =IF(A5="","",A5*B5) -> 1920
A6: 5 | B6: 220 | D6: =IF(A6="","",A6*B6) -> 1100
A7: 2 | B7: 360 | D7: =IF(A7="","",A7*B7) -> 720
A8: 33 | B8: 120 | D8: =IF(A8="","",A8*B8) -> 3960
A9: 3 | B9: 150 | D9: =IF(A9="","",A9*B9) -> 450
A10: 2 | B10: 135 | D10: =IF(A10="","",A10*B10) -> 270
A11: 2 | B11: 390 | D11: =IF(A11="","",A11*B11) -> 780
A12: 2 | B12: 340 | D12: =IF(A12="","",A12*B12) -> 680
A13: 6 | B13: 110 | D13: =IF(A13="","",A13*B13) -> 660
A14: 1 | B14: 330 | D14: =IF(A14="","",A14*B14) -> 330
A15: 1 | B15: 320 | D15: =IF(A15="","",A15*B15) -> 320
A16: 1 | B16: 260 | D16: =IF(A16="","",A16*B16) -> 260
... A22: 1 | B22: 480 | D22: =IF(A22="","",A22*B22) -> 480
D23: =IF(A23="","",A23*B23)
D24: =IF(A24="","",A24*B24)
D25: =IF(A25="","",A25*B25)
D26: =IF(A26="","",A26*B26)
D27: =IF(A27="","",A27*B27)
D28: =IF(A28="","",A28*B28)
D29: =IF(A29="","",A29*B29)
D30: =IF(A30="","",A30*B30)
D31: =IF(A31="","",A31*B31)
D32: =IF(A32="","",A32*B32)
D33: =IF(A33="","",A33*B33)
D34: =IF(A34="","",A34*B34)
... D104: =IF(A104="","",A104*B104)

Sheet Abril Vta Mat
A1: VENTA DE MATERIALES - ABRIL 2026
A2: TOTAL | B2: =SUM(B5:B54) -> 712.5
A4: CONCEPTO | B4: MONTO
A5: VENTA DE REUTER ONU 1 | B5: 160
A6: VENTA DE 67 METROS DE FIBRA OPTICA | B6: 100
A7: VENTA DE PATCH CORD 1 UNIDAD | B7: 10
A8: VENTA DE CONECTOR METALICO COAXIAL | B8: 2.5
A9: VENTA DE ONU INTERNET | B9: 190
A10: VENTA DE REUNET ONU WI FI | B10: 190
A11: VENTA DE CABLE COAXIAL 10 METROS Y 2 CONECTORES | B11: 20
A12: VENTA DE 5 METROS CABLE COAXIAL Y 2 CONECTORES | B12: 10
A13: VENTA DE CABLE COAXIAL 10 METROS Y 2 CONECTORES | B13: 30

Sheet Abril Pagos
A1: PAGOS DE: ALQUILERES, ENERGÍA, IPTU, RENTAS Y OTROS - ABRIL 2026
A2: TOTAL | B2: =SUM(B5:B54) -> 13863.6
A4: CONCEPTO | B4: MONTO
A5: PAGO ALQUILER OFICINA | B5: 400
A6: PAGO ALQUILER CABECERA | B6: 1000
A7: PAGO ENERGÍA OFICINA | B7: 31
A8: PAGO ENERGÍA CABECERA | B8: 520
A9: PAGO 02 LÍNEAS CLARO CELULAR | B9: 26.8
A10: PAGO ALQUILER POSTES ELECTRO P. | B10: 107
A11: PAGO RENTA, PRONATEL Y CONTADORA | B11: 155
A12: PAGO TÉCNICO | B12: 1800
A13: PAGO SECRETARIA | B13: 1200
A14: PAGO A. RESPONSABLE | B14: 800
A15: PAGO INTERNET CLARO | B15: 6195
A16: PAGO IPTU LIGA F Y CARLOS | B16: 1628.8

Sheet Abril gastos
A1: GASTOS OLLACHEA, COMISIONES Y OTROS - ABRIL 2026
A2: TOTAL | B2: =SUM(B5:B54) -> 845
A4: CONCEPTO | B4: MONTO
A5: 1 CUADERNO DE APUNTES PARA OFICINA | B5: 3
A6: TARJADOR PARA LAPIZ | B6: 2
A7: TRIZ PEGAMENTO | B7: 1
A8: CINTA SCOTCH PARA ROTULADO | B8: 2
A9: SOBRE MANILA PARA DINERO | B9: 1
A10: COMBUSTIBLE PARA MOTO | B10: 50
A11: ETIQUETA PARA PRECIO O NOMRE | B11: 2
A12: FOCO PARA OFICINA (SE QUEMO) | B12: 25
A13: ALMUERZO DE RECOJO DINERO QUINCENAL | B13: 27
A14: PASAJE DE RECOJO DINERO QUINCENAL | B14: 80
A15: COMPRA DE LAPIZEROS ROJO,AZUL,NEGRO | B15: 9
A16: POST NOTA | B16: 3
... A27: PRESTAMO PARA CONTADORA EN MES DE MARZO | B27: 116

Sheet Abril Compra Mat
A1: COMPRA DE MATERIALES - ABRIL 2026
A2: TOTAL | C2: =SUM(C5:C54) -> 387
A4: CONCEPTO | B4: CANTIDAD | C4: MONTO
A5: SINTONIZADOR | B5: 4 | C5: 200
A6: CABLE DROP 1 HILO DE MIL METROS | B6: 1 | C6: 165
A7: GRAPAS DE PARED | B7: 2 | C7: 18
A8: PRESINTOS NEGROS | B8: 100 | C8: 4

Sheet Mayo CTV
A1: 46143
A2: TOTAL INGRESO | B2: =D6+'Mayo Internet'!D2+'Mayo Vta Mat'!B2 -> 34861
A3: TOTAL SALIDA | B3: ='Mayo Pagos'!B2+'Mayo Gastos'!B2+'Mayo Compra Mat'!C2 -> 12959.4
A4: TOTAL NETO | B4: =B2-B3 -> 21901.6
A6: INGRESO DETALLADO CTV - MAYO 2026 | D6: =SUM(D9:D108) -> 10546
A8: CLIENTES | B8: MONTO PAGO | C8: DETALLE PAGO | D8: SUB TOTAL
A9: 39 | B9: 50 | D9: =IF(A9="","",A9*B9) -> 1950
A10: 29 | B10: 100 | D10: =IF(A10="","",A10*B10) -> 2900
A11: 9 | B11: 150 | D11: =IF(A11="","",A11*B11) -> 1350
A12: 8 | B12: 200 | D12: =IF(A12="","",A12*B12) -> 1600
A13: 5 | B13: 120 | D13: =IF(A13="","",A13*B13) -> 600
A14: 1 | B14: 30 | D14: =IF(A14="","",A14*B14) -> 30
A15: 1 | B15: 260 | D15: =IF(A15="","",A15*B15) -> 260
A16: 1 | B16: 250 | D16: =IF(A16="","",A16*B16) -> 250
A17: 1 | B17: 34 | D17: =IF(A17="","",A17*B17) -> 34
A18: 1 | B18: 285 | D18: =IF(A18="","",A18*B18) -> 285
A19: 1 | B19: 380 | D19: =IF(A19="","",A19*B19) -> 380
A20: 1 | B20: 110 | D20: =IF(A20="","",A20*B20) -> 110
... A23: 1 | B23: 240 | D23: =IF(A23="","",A23*B23) -> 240
D24: =IF(A24="","",A24*B24)
D25: =IF(A25="","",A25*B25)
D26: =IF(A26="","",A26*B26)
D27: =IF(A27="","",A27*B27)
D28: =IF(A28="","",A28*B28)
D29: =IF(A29="","",A29*B29)
D30: =IF(A30="","",A30*B30)
D31: =IF(A31="","",A31*B31)
D32: =IF(A32="","",A32*B32)
D33: =IF(A33="","",A33*B33)
D34: =IF(A34="","",A34*B34)
D35: =IF(A35="","",A35*B35)
... D108: =IF(A108="","",A108*B108)

Sheet Mayo Internet
A1: INGRESO DETALLADO INTERNET - MAYO 2026
A2: TOTAL | D2: =SUM(D5:D104) -> 23560
A4: CLIENTES | B4: MONTO PAGO | C4: DETALLE PAGO | D4: SUB TOTAL
A5: 52 | B5: 120 | D5: =IF(A5="","",A5*B5) -> 6240
A6: 26 | B6: 240 | D6: =IF(A6="","",A6*B6) -> 6240
A7: 7 | B7: 110 | D7: =IF(A7="","",A7*B7) -> 770
A8: 5 | B8: 360 | D8: =IF(A8="","",A8*B8) -> 1800
A9: 3 | B9: 220 | D9: =IF(A9="","",A9*B9) -> 660
A10: 2 | B10: 390 | D10: =IF(A10="","",A10*B10) -> 780
A11: 2 | B11: 1050 | D11: =IF(A11="","",A11*B11) -> 2100
A12: 2 | B12: 50 | D12: =IF(A12="","",A12*B12) -> 100
A13: 2 | B13: 150 | D13: =IF(A13="","",A13*B13) -> 300
A14: 1 | B14: 205 | D14: =IF(A14="","",A14*B14) -> 205
A15: 1 | B15: 1000 | D15: =IF(A15="","",A15*B15) -> 1000
A16: 1 | B16: 170 | D16: =IF(A16="","",A16*B16) -> 170
... A26: 1 | B26: 405 | D26: =IF(A26="","",A26*B26) -> 405
D27: =IF(A27="","",A27*B27)
D28: =IF(A28="","",A28*B28)
D29: =IF(A29="","",A29*B29)
D30: =IF(A30="","",A30*B30)
D31: =IF(A31="","",A31*B31)
D32: =IF(A32="","",A32*B32)
D33: =IF(A33="","",A33*B33)
D34: =IF(A34="","",A34*B34)
D35: =IF(A35="","",A35*B35)
D36: =IF(A36="","",A36*B36)
D37: =IF(A37="","",A37*B37)
D38: =IF(A38="","",A38*B38)
... D104: =IF(A104="","",A104*B104)

Sheet Mayo Vta Mat
A1: VENTA DE MATERIALES - MAYO 2026
A2: TOTAL | B2: =SUM(B5:B54) -> 755
A4: CONCEPTO | B4: MONTO
A5: CABLE UTP 10 MTS Y 2 CONECTORES | B5: 25
A6: CONECTOR FIBRA OPTICA | B6: 10
A7: CABLE COAXIAL 20 MTS | B7: 50
A8: CABLE UTP 12 MTS | B8: 30
A9: CONECTORES UND 4 COAXIAL | B9: 10
A10: VENTA DE CONECTORES | B10: 20
A11: CONECTORES METALICOS 02 UNIDADES | B11: 5
A12: FUENTE DE PODER | B12: 10
A13: TRIPLEXOR TELEVISION | B13: 30
A14: DROP,FIBRA 70 MTS | B14: 70
A15: SINTINIZADOR DIGITAL 1 | B15: 90
A16: CABLE RED Y 2 CONECTORES | B16: 30
... A21: VENTA DE CONTROL DE SINTONIZADOR | B21: 75

Sheet Mayo Pagos
A1: PAGOS DE: ALQUILERES, ENERGÍA, IPTU, RENTAS Y OTROS - MAYO 2026
A2: TOTAL | B2: =SUM(B5:B54) -> 10502.2
A4: CONCEPTO | B4: MONTO
A5: PAGO ALQUILER OFICINA | B5: 400
A6: PAGO ALQUILER CABECERA | B6: 1000
A7: PAGO ENERGÍA OFICINA | B7: 26.9
A8: PAGO ENERGÍA CABECERA | B8: 547.2
A9: PAGO 02 LÍNEAS CLARO CELULAR | B9: 31
A10: PAGO ALQUILER POSTES ELECTRO P. | B10: 110
A11: PAGO RENTA, PRONATEL Y CONTADORA | B11: 145
A12: PAGO TÉCNICO | B12: 1800
A13: PAGO SECRETARIA | B13: 1200
A14: PAGO A. RESPONSABLE | B14: 800
A15: PAGO INTERNET CLARO | B15: 3123.1
A16: PAGO IPTU LIGA F Y CARLOS | B16: 1319

Sheet Mayo Gastos
A1: GASTOS OLLACHEA, COMISIONES Y OTROS - MAYO 2026
A2: TOTAL | B2: =SUM(B5:B54) -> 1800
A4: CONCEPTO | B4: MONTO
A5: ALQUILER LOCAL PARA EQUIPOS | B5: 56
A6: DETERGENTE OFICINA | B6: 10
A7: GASOLINA MOTO | B7: 50
A8: GASOLINA MOTOR CABECERA | B8: 30
A9: POETT OFICINA | B9: 5
A10: AMBIENTADOR | B10: 10
A11: BOLSAS PARA BASURA | B11: 10
A12: POETT CABECERA | B12: 5
A13: JABON LIQUIDO PARA MANO | B13: 6
A14: PASAJE A PUNO TEMA DE ELECTRO ( ANGEL) | B14: 40
A15: PAGO SU DIARIO A (ANGEL) | B15: 50
A16: SE DIO A ELECTRO DEL AÑO 2024 ( PROYECTO) | B16: 700
... A26: ALMUERZO CON ELECTRO EN PUNO TEMA AMPLIACION (ANGEL) | B26: 20

Sheet Mayo Compra Mat
A1: COMPRA DE MATERIALES - MAYO 2026
A2: TOTAL | C2: =SUM(C5:C54) -> 657.2
A4: CONCEPTO | B4: CANTIDAD | C4: MONTO
A5: CONECTORES RAPIDOS | B5: 100 UND | C5: 198.2
A6: RACK PARA TELEVISION | B6: 1 | C6: 64
A7: 2 CUADERNOS ANILLADOS | B7: 2 | C7: 25
A8: CABLE DROP DE 1 HILO | B8: 1 | C8: 185
A9: UN CIENTO DE CONECTORES METALILOS | B9: 1 CIENTO | C9: 85
A10: CABLE PACHCORD CADA UNO 2.50 | B10: 40 | C10: 100

Sheet Junio CTV
A1: 46174
A2: TOTAL INGRESO | B2: =D6+'Junio Internet'!D2+'Junio Vta Mat'!B2 -> 22873
A3: TOTAL SALIDA | B3: ='Junio Pagos'!B2+'Junio Gastos'!B2+'Junio Compra Mat'!C2 -> 13869.84
A4: TOTAL NETO | B4: =B2-B3 -> 9003.16
A6: INGRESO DETALLADO CTV - JUNIO 2026 | D6: =SUM(D9:D108) -> 7633
A8: CLIENTES | B8: MONTO PAGO | C8: DETALLE PAGO | D8: SUB TOTAL
A9: 14 | B9: 120 | D9: =IF(A9="","",A9*B9) -> 1680
A10: 60 | B10: 50 | D10: =IF(A10="","",A10*B10) -> 3000
A11: 11 | B11: 100 | D11: =IF(A11="","",A11*B11) -> 1100
A12: 5 | B12: 150 | D12: =IF(A12="","",A12*B12) -> 750
A13: 1 | B13: 167 | D13: =IF(A13="","",A13*B13) -> 167
A14: 1 | B14: 66 | D14: =IF(A14="","",A14*B14) -> 66
A15: 1 | B15: 195 | D15: =IF(A15="","",A15*B15) -> 195
A16: 1 | B16: 75 | D16: =IF(A16="","",A16*B16) -> 75
A17: 1 | B17: 200 | D17: =IF(A17="","",A17*B17) -> 200
A18: 1 | B18: 70 | D18: =IF(A18="","",A18*B18) -> 70
A19: 1 | B19: 80 | D19: =IF(A19="","",A19*B19) -> 80
A20: 1 | B20: 250 | D20: =IF(A20="","",A20*B20) -> 250
A21: 1 | D21: =IF(A21="","",A21*B21) -> 0
D22: =IF(A22="","",A22*B22)
D23: =IF(A23="","",A23*B23)
D24: =IF(A24="","",A24*B24)
D25: =IF(A25="","",A25*B25)
D26: =IF(A26="","",A26*B26)
D27: =IF(A27="","",A27*B27)
D28: =IF(A28="","",A28*B28)
D29: =IF(A29="","",A29*B29)
D30: =IF(A30="","",A30*B30)
D31: =IF(A31="","",A31*B31)
D32: =IF(A32="","",A32*B32)
D33: =IF(A33="","",A33*B33)
... D108: =IF(A108="","",A108*B108)

Sheet Junio Internet
A1: INGRESO DETALLADO INTERNET - JUNIO 2026
A2: TOTAL | D2: =SUM(D5:D104) -> 15025
A4: CLIENTES | B4: MONTO PAGO | C4: DETALLE PAGO | D4: SUB TOTAL
A5: 43 | B5: 120 | D5: =IF(A5="","",A5*B5) -> 5160
A6: 10 | B6: 110 | D6: =IF(A6="","",A6*B6) -> 1100
A7: 3 | B7: 390 | D7: =IF(A7="","",A7*B7) -> 1170
A8: 6 | B8: 240 | D8: =IF(A8="","",A8*B8) -> 1440
A9: 2 | B9: 220 | D9: =IF(A9="","",A9*B9) -> 440
A10: 2 | B10: 380 | D10: =IF(A10="","",A10*B10) -> 760
A11: 1 | B11: 50 | D11: =IF(A11="","",A11*B11) -> 50
A12: 1 | B12: 480 | D12: =IF(A12="","",A12*B12) -> 480
A13: 1 | B13: 330 | D13: =IF(A13="","",A13*B13) -> 330
A14: 1 | B14: 150 | D14: =IF(A14="","",A14*B14) -> 150
A15: 1 | B15: 360 | D15: =IF(A15="","",A15*B15) -> 360
A16: 1 | B16: 130 | D16: =IF(A16="","",A16*B16) -> 130
... A21: 1 | B21: 1050 | D21: =IF(A21="","",A21*B21) -> 1050
D22: =IF(A22="","",A22*B22)
D23: =IF(A23="","",A23*B23)
D24: =IF(A24="","",A24*B24)
D25: =IF(A25="","",A25*B25)
D26: =IF(A26="","",A26*B26)
D27: =IF(A27="","",A27*B27)
D28: =IF(A28="","",A28*B28)
D29: =IF(A29="","",A29*B29)
D30: =IF(A30="","",A30*B30)
D31: =IF(A31="","",A31*B31)
D32: =IF(A32="","",A32*B32)
D33: =IF(A33="","",A33*B33)
... D104: =IF(A104="","",A104*B104)

Sheet Junio Vta Mat
A1: VENTA DE MATERIALES - JUNIO 2026
A2: 1 | B2: =SUM(B5:B54) -> 215
A4: CONCEPTO | B4: MONTO
A5: 10 mts de cable coaxial y 2 conectores | B5: 30
A6: 5 mts de cable coaxial y 2 conectores metalicos | B6: 20
A7: venta de 1 sintonizador digital | B7: 90
A8: venta de espliter de 2 salidas y cable coaxial 10 mts | B8: 40
A9: venta de 10 mts cable coaxial y 4 conectores metalicos | B9: 35

Sheet Junio Pagos
A1: PAGOS DE: ALQUILERES, ENERGÍA, IPTU, RENTAS Y OTROS - JUNIO 2026
A2: TOTAL | B2: =SUM(B5:B54) -> 10450.6
A4: CONCEPTO | B4: MONTO
A5: PAGO ALQUILER OFICINA | B5: 400
A6: PAGO ALQUILER CABECERA | B6: 1000
A7: PAGO ENERGÍA OFICINA
A8: PAGO ENERGÍA CABECERA | B8: 517.5
A9: PAGO 02 LÍNEAS CLARO CELULAR | B9: 30
A10: PAGO ALQUILER POSTES ELECTRO P. | B10: 106
A11: PAGO RENTA, PRONATEL Y CONTADORA | B11: 155
A12: PAGO TÉCNICO | B12: 1800
A13: PAGO SECRETARIA | B13: 1200
A14: PAGO A. RESPONSABLE | B14: 800
A15: PAGO INTERNET CLARO | B15: 3123.1
A16: PAGO IPTV LIGA 1 Y CARLOS | B16: 1319

Sheet Junio Gastos
A1: GASTOS OLLACHEA, COMISIONES Y OTROS - JUNIO 2026
A2: TOTAL | B2: =SUM(B5:B54) -> 611
A4: CONCEPTO | B4: MONTO
A5: ACCESORIOS REPUESTOS LAVAMANOS | B5: 24
A6: LEJIA Y POETT OFICINA 11/06/26 | B6: 5
A7: BALON DEGAS | B7: 65
A8: ACCESORIOS COCINA (MANGUERA Y HORNILLA) | B8: 42
A9: COMBUSTIBLE MOTO | B9: 50
A10: GRAPAS 2 PAQUETES A 8 SOLES | B10: 16
A11: ALMUERZO POR TRASLADO DE OFICINA | B11: 24
A12: MICAS PARA AVISO NUEVA OFICINA | B12: 2
A13: POETT PARA OFICINA NUEVA | B13: 5
A14: BROCA PARA CONCRETRO PARA NUEVA OFICINA RACK | B14: 12
A15: IMPRESIÓN AVISOS PARA NUEVA OFICINA | B15: 1
A16: RECOJO DE ONUS AREQUIPA SAN ANTON (RONAL) | B16: 30
... A23: DESAYUNO RECOJO DINERO FIN DE MES | B23: 16

Sheet Junio Compra Mat
A1: COMPRA DE MATERIALES - JUNIO 2026
A2: TOTAL | C2: =SUM(C5:C54) -> 2808.24
A4: CONCEPTO | B4: CANTIDAD | C4: MONTO
A5: COMPRA DE ONUS CADA UNO A 125 | B5: 15 | C5: 1875
A6: COMPRA DE SINTONIZADORES DIGITALES MAS COMISION | B6: 10 | C6: 510
A7: COMPRA DE CABLE UTP CAT6 305 MTS | B7: 1 | C7: 225
A8: COMPRA DE CONECTORES METALICOS | B8: 100 | C8: 198.24

Sheet Julio CTV
A1: JULIO 2025
A2: TOTAL INGRESO | B2: =D6+'Julio Internet'!D2+'Julio Vta Mat'!B2 -> 0
A3: TOTAL SALIDA | B3: ='Julio Pagos'!B2+'Julio Gastos'!B2+'Julio Compra Mat'!C2 -> 0
A4: TOTAL NETO | B4: =B2-B3 -> 0
A6: INGRESO DETALLADO CTV - JULIO 2025 | D6: =SUM(D9:D108) -> 0
A8: CLIENTES | B8: MONTO PAGO | C8: DETALLE PAGO | D8: SUB TOTAL
D9: =IF(A9="","",A9*B9)
D10: =IF(A10="","",A10*B10)
D11: =IF(A11="","",A11*B11)
D12: =IF(A12="","",A12*B12)
D13: =IF(A13="","",A13*B13)
D14: =IF(A14="","",A14*B14)
D15: =IF(A15="","",A15*B15)
D16: =IF(A16="","",A16*B16)
D17: =IF(A17="","",A17*B17)
D18: =IF(A18="","",A18*B18)
D19: =IF(A19="","",A19*B19)
D20: =IF(A20="","",A20*B20)
... D108: =IF(A108="","",A108*B108)

Sheet Julio Internet
A1: INGRESO DETALLADO INTERNET - JULIO 2025
A2: TOTAL | D2: =SUM(D5:D104) -> 0
A4: CLIENTES | B4: MONTO PAGO | C4: DETALLE PAGO | D4: SUB TOTAL
D5: =IF(A5="","",A5*B5)
D6: =IF(A6="","",A6*B6)
D7: =IF(A7="","",A7*B7)
D8: =IF(A8="","",A8*B8)
D9: =IF(A9="","",A9*B9)
D10: =IF(A10="","",A10*B10)
D11: =IF(A11="","",A11*B11)
D12: =IF(A12="","",A12*B12)
D13: =IF(A13="","",A13*B13)
D14: =IF(A14="","",A14*B14)
D15: =IF(A15="","",A15*B15)
D16: =IF(A16="","",A16*B16)
... D104: =IF(A104="","",A104*B104)

Sheet Julio Vta Mat
A1: VENTA DE MATERIALES - JULIO 2025
A2: TOTAL | B2: =SUM(B5:B54) -> 0
A4: CONCEPTO | B4: MONTO

Sheet Julio Pagos
A1: PAGOS DE: ALQUILERES, ENERGÍA, IPTU, RENTAS Y OTROS - JULIO 2025
A2: TOTAL | B2: =SUM(B5:B54) -> 0
A4: CONCEPTO | B4: MONTO
A5: PAGO ALQUILER OFICINA
A6: PAGO ALQUILER CABECERA
A7: PAGO ENERGÍA OFICINA
A8: PAGO ENERGÍA CABECERA
A9: PAGO 02 LÍNEAS CLARO CELULAR
A10: PAGO ALQUILER POSTES ELECTRO P.
A11: PAGO RENTA, PRONATEL Y CONTADORA
A12: PAGO TÉCNICO
A13: PAGO SECRETARIA
A14: PAGO A. RESPONSABLE
A15: PAGO INTERNET CLARO
A16: PAGO IPTU LIGA F Y CARLOS
... A19: POR COMPRA Y TRASLADO DE CANASTAS

Sheet Julio Gastos
A1: GASTOS OLLACHEA, COMISIONES Y OTROS - JULIO 2025
A2: TOTAL | B2: =SUM(B5:B54) -> 0
A4: CONCEPTO | B4: MONTO

Sheet Julio Compra Mat
A1: COMPRA DE MATERIALES - JULIO 2025
A2: TOTAL | C2: =SUM(C5:C54) -> 0
A4: CONCEPTO | B4: CANTIDAD | C4: MONTO

Sheet Agosto CTV
A1: AGOSTO 2025
A2: TOTAL INGRESO | B2: =D6+'Agosto Internet'!D2+'Agosto Vta Mat'!B2 -> 0
A3: TOTAL SALIDA | B3: ='Agosto Pagos'!B2+'Agosto Gastos'!B2+'Agosto Compra Mat'!C2 -> 0
A4: TOTAL NETO | B4: =B2-B3 -> 0
A6: INGRESO DETALLADO CTV - AGOSTO 2025 | D6: =SUM(D9:D108) -> 0
A8: CLIENTES | B8: MONTO PAGO | C8: DETALLE PAGO | D8: SUB TOTAL
D9: =IF(A9="","",A9*B9)
D10: =IF(A10="","",A10*B10)
D11: =IF(A11="","",A11*B11)
D12: =IF(A12="","",A12*B12)
D13: =IF(A13="","",A13*B13)
D14: =IF(A14="","",A14*B14)
D15: =IF(A15="","",A15*B15)
D16: =IF(A16="","",A16*B16)
D17: =IF(A17="","",A17*B17)
D18: =IF(A18="","",A18*B18)
D19: =IF(A19="","",A19*B19)
D20: =IF(A20="","",A20*B20)
... D108: =IF(A108="","",A108*B108)

Sheet Agosto Internet
A1: INGRESO DETALLADO INTERNET - AGOSTO 2025
A2: TOTAL | D2: =SUM(D5:D104) -> 0
A4: CLIENTES | B4: MONTO PAGO | C4: DETALLE PAGO | D4: SUB TOTAL
D5: =IF(A5="","",A5*B5)
D6: =IF(A6="","",A6*B6)
D7: =IF(A7="","",A7*B7)
D8: =IF(A8="","",A8*B8)
D9: =IF(A9="","",A9*B9)
D10: =IF(A10="","",A10*B10)
D11: =IF(A11="","",A11*B11)
D12: =IF(A12="","",A12*B12)
D13: =IF(A13="","",A13*B13)
D14: =IF(A14="","",A14*B14)
D15: =IF(A15="","",A15*B15)
D16: =IF(A16="","",A16*B16)
... D104: =IF(A104="","",A104*B104)

Sheet Agosto Vta Mat
A1: VENTA DE MATERIALES - AGOSTO 2025
A2: TOTAL | B2: =SUM(B5:B54) -> 0
A4: CONCEPTO | B4: MONTO

Sheet Agosto Pagos
A1: PAGOS DE: ALQUILERES, ENERGÍA, IPTU, RENTAS Y OTROS - AGOSTO 2025
A2: TOTAL | B2: =SUM(B5:B54) -> 0
A4: CONCEPTO | B4: MONTO
A5: PAGO ALQUILER OFICINA
A6: PAGO ALQUILER CABECERA
A7: PAGO ENERGÍA OFICINA
A8: PAGO ENERGÍA CABECERA
A9: PAGO 02 LÍNEAS CLARO CELULAR
A10: PAGO ALQUILER POSTES ELECTRO P.
A11: PAGO RENTA, PRONATEL Y CONTADORA
A12: PAGO TÉCNICO
A13: PAGO SECRETARIA
A14: PAGO A. RESPONSABLE
A15: PAGO INTERNET CLARO
A16: PAGO IPTU LIGA F Y CARLOS
... A19: POR COMPRA Y TRASLADO DE CANASTAS

Sheet Agosto Gastos
A1: GASTOS OLLACHEA, COMISIONES Y OTROS - AGOSTO 2025
A2: TOTAL | B2: =SUM(B5:B54) -> 0
A4: CONCEPTO | B4: MONTO

Sheet Agosto Compra Mat
A1: COMPRA DE MATERIALES - AGOSTO 2025
A2: TOTAL | C2: =SUM(C5:C54) -> 0
A4: CONCEPTO | B4: CANTIDAD | C4: MONTO

Sheet Septiembre CTV
A1: SEPTIEMBRE 2025
A2: TOTAL INGRESO | B2: =D6+'Septiembre Internet'!D2+'Septiembre Vta Mat'!B2 -> 0
A3: TOTAL SALIDA | B3: ='Septiembre Pagos'!B2+'Septiembre Gastos'!B2+'Septiembre Compra Mat'!C2 -> 0
A4: TOTAL NETO | B4: =B2-B3 -> 0
A6: INGRESO DETALLADO CTV - SEPTIEMBRE 2025 | D6: =SUM(D9:D108) -> 0
A8: CLIENTES | B8: MONTO PAGO | C8: DETALLE PAGO | D8: SUB TOTAL
D9: =IF(A9="","",A9*B9)
D10: =IF(A10="","",A10*B10)
D11: =IF(A11="","",A11*B11)
D12: =IF(A12="","",A12*B12)
D13: =IF(A13="","",A13*B13)
D14: =IF(A14="","",A14*B14)
D15: =IF(A15="","",A15*B15)
D16: =IF(A16="","",A16*B16)
D17: =IF(A17="","",A17*B17)
D18: =IF(A18="","",A18*B18)
D19: =IF(A19="","",A19*B19)
D20: =IF(A20="","",A20*B20)
... D108: =IF(A108="","",A108*B108)

Sheet Septiembre Internet
A1: INGRESO DETALLADO INTERNET - SEPTIEMBRE 2025
A2: TOTAL | D2: =SUM(D5:D104) -> 0
A4: CLIENTES | B4: MONTO PAGO | C4: DETALLE PAGO | D4: SUB TOTAL
D5: =IF(A5="","",A5*B5)
D6: =IF(A6="","",A6*B6)
D7: =IF(A7="","",A7*B7)
D8: =IF(A8="","",A8*B8)
D9: =IF(A9="","",A9*B9)
D10: =IF(A10="","",A10*B10)
D11: =IF(A11="","",A11*B11)
D12: =IF(A12="","",A12*B12)
D13: =IF(A13="","",A13*B13)
D14: =IF(A14="","",A14*B14)
D15: =IF(A15="","",A15*B15)
D16: =IF(A16="","",A16*B16)
... D104: =IF(A104="","",A104*B104)

Sheet Septiembre Vta Mat
A1: VENTA DE MATERIALES - SEPTIEMBRE 2025
A2: TOTAL | B2: =SUM(B5:B54) -> 0
A4: CONCEPTO | B4: MONTO

Sheet Septiembre Pagos
A1: PAGOS DE: ALQUILERES, ENERGÍA, IPTU, RENTAS Y OTROS - SEPTIEMBRE 2025
A2: TOTAL | B2: =SUM(B5:B54) -> 0
A4: CONCEPTO | B4: MONTO
A5: PAGO ALQUILER OFICINA
A6: PAGO ALQUILER CABECERA
A7: PAGO ENERGÍA OFICINA
A8: PAGO ENERGÍA CABECERA
A9: PAGO 02 LÍNEAS CLARO CELULAR
A10: PAGO ALQUILER POSTES ELECTRO P.
A11: PAGO RENTA, PRONATEL Y CONTADORA
A12: PAGO TÉCNICO
A13: PAGO SECRETARIA
A14: PAGO A. RESPONSABLE
A15: PAGO INTERNET CLARO
A16: PAGO IPTU LIGA F Y CARLOS
... A19: POR COMPRA Y TRASLADO DE CANASTAS

Sheet Septiembre Gastos
A1: GASTOS OLLACHEA, COMISIONES Y OTROS - SEPTIEMBRE 2025
A2: TOTAL | B2: =SUM(B5:B54) -> 0
A4: CONCEPTO | B4: MONTO

Sheet Septiembre Compra Mat
A1: COMPRA DE MATERIALES - SEPTIEMBRE 2025
A2: TOTAL | C2: =SUM(C5:C54) -> 0
A4: CONCEPTO | B4: CANTIDAD | C4: MONTO

Sheet Octubre CTV
A1: OCTUBRE 2025
A2: TOTAL INGRESO | B2: =D6+'Octubre Internet'!D2+'Octubre Vta Mat'!B2 -> 0
A3: TOTAL SALIDA | B3: ='Octubre Pagos'!B2+'Octubre Gastos'!B2+'Octubre Compra Mat'!C2 -> 0
A4: TOTAL NETO | B4: =B2-B3 -> 0
A6: INGRESO DETALLADO CTV - OCTUBRE 2025 | D6: =SUM(D9:D108) -> 0
A8: CLIENTES | B8: MONTO PAGO | C8: DETALLE PAGO | D8: SUB TOTAL
D9: =IF(A9="","",A9*B9)
D10: =IF(A10="","",A10*B10)
D11: =IF(A11="","",A11*B11)
D12: =IF(A12="","",A12*B12)
D13: =IF(A13="","",A13*B13)
D14: =IF(A14="","",A14*B14)
D15: =IF(A15="","",A15*B15)
D16: =IF(A16="","",A16*B16)
D17: =IF(A17="","",A17*B17)
D18: =IF(A18="","",A18*B18)
D19: =IF(A19="","",A19*B19)
D20: =IF(A20="","",A20*B20)
... D108: =IF(A108="","",A108*B108)

Sheet Octubre Internet
A1: INGRESO DETALLADO INTERNET - OCTUBRE 2025
A2: TOTAL | D2: =SUM(D5:D104) -> 0
A4: CLIENTES | B4: MONTO PAGO | C4: DETALLE PAGO | D4: SUB TOTAL
D5: =IF(A5="","",A5*B5)
D6: =IF(A6="","",A6*B6)
D7: =IF(A7="","",A7*B7)
D8: =IF(A8="","",A8*B8)
D9: =IF(A9="","",A9*B9)
D10: =IF(A10="","",A10*B10)
D11: =IF(A11="","",A11*B11)
D12: =IF(A12="","",A12*B12)
D13: =IF(A13="","",A13*B13)
D14: =IF(A14="","",A14*B14)
D15: =IF(A15="","",A15*B15)
D16: =IF(A16="","",A16*B16)
... D104: =IF(A104="","",A104*B104)

Sheet Octubre Vta Mat
A1: VENTA DE MATERIALES - OCTUBRE 2025
A2: TOTAL | B2: =SUM(B5:B54) -> 0
A4: CONCEPTO | B4: MONTO

Sheet Octubre Pagos
A1: PAGOS DE: ALQUILERES, ENERGÍA, IPTU, RENTAS Y OTROS - OCTUBRE 2025
A2: TOTAL | B2: =SUM(B5:B54) -> 0
A4: CONCEPTO | B4: MONTO
A5: PAGO ALQUILER OFICINA
A6: PAGO ALQUILER CABECERA
A7: PAGO ENERGÍA OFICINA
A8: PAGO ENERGÍA CABECERA
A9: PAGO 02 LÍNEAS CLARO CELULAR
A10: PAGO ALQUILER POSTES ELECTRO P.
A11: PAGO RENTA, PRONATEL Y CONTADORA
A12: PAGO TÉCNICO
A13: PAGO SECRETARIA
A14: PAGO A. RESPONSABLE
A15: PAGO INTERNET CLARO
A16: PAGO IPTU LIGA F Y CARLOS
... A19: POR COMPRA Y TRASLADO DE CANASTAS

Sheet Octubre Gastos
A1: GASTOS OLLACHEA, COMISIONES Y OTROS - OCTUBRE 2025
A2: TOTAL | B2: =SUM(B5:B54) -> 0
A4: CONCEPTO | B4: MONTO

Sheet Octubre Compra Mat
A1: COMPRA DE MATERIALES - OCTUBRE 2025
A2: TOTAL | C2: =SUM(C5:C54) -> 0
A4: CONCEPTO | B4: CANTIDAD | C4: MONTO

Sheet Noviembre CTV
A1: NOVIEMBRE 2025
A2: TOTAL INGRESO | B2: =D6+'Noviembre Internet'!D2+'Noviembre Vta Mat'!B2 -> 0
A3: TOTAL SALIDA | B3: ='Noviembre Pagos'!B2+'Noviembre Gastos'!B2+'Noviembre Compra Mat'!C2 -> 0
A4: TOTAL NETO | B4: =B2-B3 -> 0
A6: INGRESO DETALLADO CTV - NOVIEMBRE 2025 | D6: =SUM(D9:D108) -> 0
A8: CLIENTES | B8: MONTO PAGO | C8: DETALLE PAGO | D8: SUB TOTAL
D9: =IF(A9="","",A9*B9)
D10: =IF(A10="","",A10*B10)
D11: =IF(A11="","",A11*B11)
D12: =IF(A12="","",A12*B12)
D13: =IF(A13="","",A13*B13)
D14: =IF(A14="","",A14*B14)
D15: =IF(A15="","",A15*B15)
D16: =IF(A16="","",A16*B16)
D17: =IF(A17="","",A17*B17)
D18: =IF(A18="","",A18*B18)
D19: =IF(A19="","",A19*B19)
D20: =IF(A20="","",A20*B20)
... D108: =IF(A108="","",A108*B108)

Sheet Noviembre Internet
A1: INGRESO DETALLADO INTERNET - NOVIEMBRE 2025
A2: TOTAL | D2: =SUM(D5:D104) -> 0
A4: CLIENTES | B4: MONTO PAGO | C4: DETALLE PAGO | D4: SUB TOTAL
D5: =IF(A5="","",A5*B5)
D6: =IF(A6="","",A6*B6)
D7: =IF(A7="","",A7*B7)
D8: =IF(A8="","",A8*B8)
D9: =IF(A9="","",A9*B9)
D10: =IF(A10="","",A10*B10)
D11: =IF(A11="","",A11*B11)
D12: =IF(A12="","",A12*B12)
D13: =IF(A13="","",A13*B13)
D14: =IF(A14="","",A14*B14)
D15: =IF(A15="","",A15*B15)
D16: =IF(A16="","",A16*B16)
... D104: =IF(A104="","",A104*B104)

Sheet Noviembre Vta Mat
A1: VENTA DE MATERIALES - NOVIEMBRE 2025
A2: TOTAL | B2: =SUM(B5:B54) -> 0
A4: CONCEPTO | B4: MONTO

Sheet Noviembre Pagos
A1: PAGOS DE: ALQUILERES, ENERGÍA, IPTU, RENTAS Y OTROS - NOVIEMBRE 2025
A2: TOTAL | B2: =SUM(B5:B54) -> 0
A4: CONCEPTO | B4: MONTO
A5: PAGO ALQUILER OFICINA
A6: PAGO ALQUILER CABECERA
A7: PAGO ENERGÍA OFICINA
A8: PAGO ENERGÍA CABECERA
A9: PAGO 02 LÍNEAS CLARO CELULAR
A10: PAGO ALQUILER POSTES ELECTRO P.
A11: PAGO RENTA, PRONATEL Y CONTADORA
A12: PAGO TÉCNICO
A13: PAGO SECRETARIA
A14: PAGO A. RESPONSABLE
A15: PAGO INTERNET CLARO
A16: PAGO IPTU LIGA F Y CARLOS
... A19: POR COMPRA Y TRASLADO DE CANASTAS

Sheet Noviembre Gastos
A1: GASTOS OLLACHEA, COMISIONES Y OTROS - NOVIEMBRE 2025
A2: TOTAL | B2: =SUM(B5:B54) -> 0
A4: CONCEPTO | B4: MONTO

Sheet Noviembre Compra Mat
A1: COMPRA DE MATERIALES - NOVIEMBRE 2025
A2: TOTAL | C2: =SUM(C5:C54) -> 0
A4: CONCEPTO | B4: CANTIDAD | C4: MONTO

Sheet Diciembre CTV
A1: DICIEMBRE 2025
A2: TOTAL INGRESO | B2: =D6+'Diciembre Internet'!D2+'Diciembre Vta Mat'!B2 -> 0
A3: TOTAL SALIDA | B3: ='Diciembre Pagos'!B2+'Diciembre Gastos'!B2+'Diciembre Compra Mat'!C2 -> 0
A4: TOTAL NETO | B4: =B2-B3 -> 0
A6: INGRESO DETALLADO CTV - DICIEMBRE 2025 | D6: =SUM(D9:D108) -> 0
A8: CLIENTES | B8: MONTO PAGO | C8: DETALLE PAGO | D8: SUB TOTAL
D9: =IF(A9="","",A9*B9)
D10: =IF(A10="","",A10*B10)
D11: =IF(A11="","",A11*B11)
D12: =IF(A12="","",A12*B12)
D13: =IF(A13="","",A13*B13)
D14: =IF(A14="","",A14*B14)
D15: =IF(A15="","",A15*B15)
D16: =IF(A16="","",A16*B16)
D17: =IF(A17="","",A17*B17)
D18: =IF(A18="","",A18*B18)
D19: =IF(A19="","",A19*B19)
D20: =IF(A20="","",A20*B20)
... D108: =IF(A108="","",A108*B108)

Sheet Diciembre Internet
A1: INGRESO DETALLADO INTERNET - DICIEMBRE 2025
A2: TOTAL | D2: =SUM(D5:D104) -> 0
A4: CLIENTES | B4: MONTO PAGO | C4: DETALLE PAGO | D4: SUB TOTAL
D5: =IF(A5="","",A5*B5)
D6: =IF(A6="","",A6*B6)
D7: =IF(A7="","",A7*B7)
D8: =IF(A8="","",A8*B8)
D9: =IF(A9="","",A9*B9)
D10: =IF(A10="","",A10*B10)
D11: =IF(A11="","",A11*B11)
D12: =IF(A12="","",A12*B12)
D13: =IF(A13="","",A13*B13)
D14: =IF(A14="","",A14*B14)
D15: =IF(A15="","",A15*B15)
D16: =IF(A16="","",A16*B16)
... D104: =IF(A104="","",A104*B104)

Sheet Diciembre Vta Mat
A1: VENTA DE MATERIALES - DICIEMBRE 2025
A2: TOTAL | B2: =SUM(B5:B54) -> 0
A4: CONCEPTO | B4: MONTO

Sheet Diciembre Pagos
A1: PAGOS DE: ALQUILERES, ENERGÍA, IPTU, RENTAS Y OTROS - DICIEMBRE 2025
A2: TOTAL | B2: =SUM(B5:B54) -> 0
A4: CONCEPTO | B4: MONTO
A5: PAGO ALQUILER OFICINA
A6: PAGO ALQUILER CABECERA
A7: PAGO ENERGÍA OFICINA
A8: PAGO ENERGÍA CABECERA
A9: PAGO 02 LÍNEAS CLARO CELULAR
A10: PAGO ALQUILER POSTES ELECTRO P.
A11: PAGO RENTA, PRONATEL Y CONTADORA
A12: PAGO TÉCNICO
A13: PAGO SECRETARIA
A14: PAGO A. RESPONSABLE
A15: PAGO INTERNET CLARO
A16: PAGO IPTU LIGA F Y CARLOS
... A19: POR COMPRA Y TRASLADO DE CANASTAS

Sheet Diciembre Gastos
A1: GASTOS OLLACHEA, COMISIONES Y OTROS - DICIEMBRE 2025
A2: TOTAL | B2: =SUM(B5:B54) -> 0
A4: CONCEPTO | B4: MONTO

Sheet Diciembre Compra Mat
A1: COMPRA DE MATERIALES - DICIEMBRE 2025
A2: TOTAL | C2: =SUM(C5:C54) -> 0
A4: CONCEPTO | B4: CANTIDAD | C4: MONTO
